README.rst
ghostboard.py
setup.py
ghostboard.egg-info/PKG-INFO
ghostboard.egg-info/SOURCES.txt
ghostboard.egg-info/dependency_links.txt
ghostboard.egg-info/entry_points.txt
ghostboard.egg-info/requires.txt
ghostboard.egg-info/top_level.txt