Metadata-Version: 1.1
Name: ghostboard
Version: 0.1
Summary: Start it with a filepath and it will write everything you copy to the system clipboard to a file
Home-page: http://github.com/Jaymon/ghostboard
Author: Jay Marcyes
Author-email: jay@marcyes.com
License: MIT
Platform: UNKNOWN
Classifier: Development Status :: 4 - Beta
Classifier: Environment :: Console
Classifier: Intended Audience :: End Users/Desktop
Classifier: License :: OSI Approved :: MIT License
Classifier: Operating System :: OS Independent
Classifier: Topic :: Utilities
Classifier: Programming Language :: Python :: 2.7
